pytest_only/__init__.py
pytest_only/compat.py
pytest_only/ext/__init__.py
pytest_only/ext/flake8.py
pytest_only/ext/pylint.py
pytest_only/plugin.py
pytest_only/version.py
pytest_only-2.1.2.dist-info/METADATA
pytest_only-2.1.2.dist-info/WHEEL
pytest_only-2.1.2.dist-info/entry_points.txt
pytest_only-2.1.2.dist-info/RECORD
