Metadata-Version: 2.1
Name: pytest-only
Version: 2.1.2
Summary: Use @pytest.mark.only to run a single test
Home-page: https://github.com/theY4Kman/pytest-only
License: MIT
Keywords: pytest
Author: Zach Kanzler
Author-email: they4kman@gmail.com
Requires-Python: >=3.8,<4.0
Classifier: Development Status :: 5 - Production/Stable
Classifier: Framework :: Pytest
Classifier: License :: OSI Approved :: MIT License
Classifier: Programming Language :: Python
Classifier: Programming Language :: Python :: 3
Classifier: Programming Language :: Python :: 3.8
Classifier: Programming Language :: Python :: 3.9
Classifier: Programming Language :: Python :: 3.10
Classifier: Programming Language :: Python :: 3.11
Classifier: Programming Language :: Python :: 3.12
Classifier: Topic :: Software Development :: Testing
Requires-Dist: pytest (>=3.6.0,<9)
Project-URL: Repository, https://github.com/theY4Kman/pytest-only
